A1/Codes/q5.v
module q5(
    output reg Q,    
    output reg Qbar, 
    input wire J,    
    input wire K,    
    input wire clk  
);
    always @(posedge clk) begin
        if (J == 0 && K == 0) begin
            Q <= Q;
            Qbar <= Qbar;
        end else if (J == 0 && K == 1) begin
            Q <= 1'b0;
            Qbar <= 1'b1;
        end else if (J == 1 && K == 0) begin
            Q <= 1'b1;
            Qbar <= 1'b0;
        end else begin
            Q <= ~Q;
            Qbar <= ~Qbar;
        end
    end

endmodule

VLSI A1/Codes/tb_q5.v
`include "q5.v"
`timescale 1ns/1ns

module q5_tb;
    reg J, K, clk;
    wire Q, Qbar;

    q5 u1 (Q,Qbar,J,K,clk);
    initial begin
        $dumpfile("tb_q5.vcd");
        $dumpvars(0, q5_tb);
    end

    always begin
        clk = ~clk;
        #5;
    end
    
    always @(posedge clk) begin
        #5
        $display($time,"ns Q = ",Q," Qbar =",Qbar);
    end

    initial begin
        J = 0;
        K = 0;
        clk = 0;
        
        #10 J = 1; K = 0;
        #10 J = 0; K = 0;
        #10 J = 0; K = 1;
        #10 J = 0; K = 0;
        #10 J = 1; K = 1;
        #10 J = 1; K = 1;
        #10 J = 0; K = 0; 
        $finish;
    end
endmodule

A1/Codes/tb_q5.vcd
$date
	Sat Sep 16 22:24:21 2023
$end
$version
	Icarus Verilog
$end
$timescale
	1ns
$end
$scope module q5_tb $end
$var wire 1 ! Qbar $end
$var wire 1 " Q $end
$var reg 1 # J $end
$var reg 1 $ K $end
$var reg 1 % clk $end
$scope module u1 $end
$var wire 1 # J $end
$var wire 1 $ K $end
$var wire 1 % clk $end
$var reg 1 " Q $end
$var reg 1 ! Qbar $end
$upscope $end
$upscope $end
$enddefinitions $end
#0
$dumpvars
0%
0$
0#
x"
x!
$end
#5
1%
#10
0%
1#
#15
0!
1"
1%
#20
0%
0#
#25
1%
#30
0%
1$
#35
1!
0"
1%
#40
0%
0$
#45
1%
#50
0%
1$
1#
#55
0!
1"
1%
#60
0%
#65
1!
0"
1%
#70
0%
0$
0#
