VLSI A1/Codes/q6.v
module q6 (
  input clk,
  input reset,
  input in,
  output reg out
);
parameter s0 = 0, s1 = 1, s2 = 2, s3 = 3, s4 = 4;
    
reg[2:0] state,next_state;

always@(posedge clk)begin
  if(reset)begin
    state <= s0;
  end
  else begin
    state <= next_state;
  end
end

always@(state or in)begin
  case(state)
    s0:begin
      out = 0;
      if(in) next_state = s1;
      else next_state = s0;
    end
    s1:begin
        out = 0;
        if(in) next_state = s1;
        else next_state = s2;
    end
    s2:begin
      out = 0;
      if(in) next_state = s3;
      else next_state = s0;
    end
    s3:begin
      out = 0;
      if(in) next_state = s4;
      else next_state = s2;
    end
    s4:begin
        out = 1;
        if(in) next_state = s1;
        else next_state = s2;
    end
    default:begin
      next_state = s0;
    end
  endcase
  end
endmodule

A1/Codes/tb_q6.v
`include "q6.v"
`timescale 1ns/1ns
module q6_tb;
reg clk,in;
reg rst_n;
wire out;

q6 call(clk,rst_n,in,out);
always #5 clk = ~clk;
initial begin
    $dumpfile("tb_q6.vcd");
    $dumpvars(0, q6_tb);
end

always @(posedge clk) begin
    #10
    $display($time,"ns in = ",in," out =",out);
end

initial begin
    clk = 1;
    rst_n =1;
    in =0;
end

initial begin
    #10;
    rst_n = 0;
    in = 1;
    #10
    rst_n = 0;
    in = 1;
    #10
    rst_n = 0;
    in = 0;
    #10
    rst_n = 0;
    in = 1;
    #10
    rst_n = 0;
    in = 1;
    #10
    rst_n = 0;
    in = 0;
    #10
    rst_n = 0;
    in = 1;
    #10
    rst_n = 0;
    in = 1;
    #10
    // rst_n = 0;
    // in = 1;
    // #10
    // rst_n = 0;
    // in = 1;
    // #10
    // rst_n = 0;
    // in = 0;
    #10
    $finish;
end
endmodule

A1/Codes/tb_q6.vcd
$date
	Sat Sep 16 22:48:39 2023
$end
$version
	Icarus Verilog
$end
$timescale
	1ns
$end
$scope module q6_tb $end
$var wire 1 ! out $end
$var reg 1 " clk $end
$var reg 1 # in $end
$var reg 1 $ rst_n $end
$scope module call $end
$var wire 1 " clk $end
$var wire 1 # in $end
$var wire 1 $ reset $end
$var reg 3 % next_state [2:0] $end
$var reg 1 ! out $end
$var reg 3 & state [2:0] $end
$upscope $end
$upscope $end
$enddefinitions $end
#0
$dumpvars
b0 &
b0 %
1$
0#
1"
0!
$end
#5
0"
#10
b1 &
b1 %
1"
1#
0$
#15
0"
#20
1"
#25
0"
#30
b10 &
b0 %
1"
0#
#35
0"
#40
b11 &
b100 %
1"
1#
#45
0"
#50
b1 %
1!
b100 &
1"
#55
0"
#60
0!
b10 &
b0 %
1"
0#
#65
0"
#70
b11 &
b100 %
1"
1#
#75
0"
#80
b1 %
1!
b100 &
1"
#85
0"
#90
0!
b1 &
1"
