VLSI A1/Codes/q8.v
module q8(A,B,EQ,GT);
    input [1:0] A;
    input [1:0] B;
    output EQ,GT;
    wire t1;
    assign t1 = (A[1]~^B[1]);
    assign EQ = ((A[1]~^B[1]) &  (A[0]~^B[0]));
    assign GT = ((A[1] & ~B[1]) | (t1 & A[0] & ~B[0]));
endmodule

A1/Codes/tb_q8.v
`include "q8.v"

module q8_tb;
    reg [1:0] A;
    reg [1:0] B;
    wire EQ, GT;

    q8 DUT (.A(A),.B(B),.EQ(EQ),.GT(GT));

    initial begin
        $dumpfile("tb_q8.vcd");
        $dumpvars(0,q8_tb);
        $monitor ($time, " A=%b, B=%b, EQ=%b, GT=%b", A, B, EQ, GT);
        A = 2'b10;
        B = 2'b01;
        #10; 
        A = 2'b11;
        B = 2'b11;
        #10;
        A = 2'b01;
        B = 2'b10;
        #10;
        A = 2'b01;
        B = 2'b00;
        #10
        A = 2'b00;
        B = 2'b01;
        #10
        A = 2'b00;
        B = 2'b00;
        #10
        A = 2'b10;
        B = 2'b00;
        #10
        A = 2'b01;
        B = 2'b00;
        #10
        A = 2'b11;
        B = 2'b00;
        #10
        A = 2'b00;
        B = 2'b11;
        #10
        $finish;
    end
endmodule

A1/Codes/tb_q8.vcd
$date
	Sat Sep 16 22:50:33 2023
$end
$version
	Icarus Verilog
$end
$timescale
	1s
$end
$scope module q8_tb $end
$var wire 1 ! GT $end
$var wire 1 " EQ $end
$var reg 2 # A [1:0] $end
$var reg 2 $ B [1:0] $end
$scope module DUT $end
$var wire 2 % A [1:0] $end
$var wire 2 & B [1:0] $end
$var wire 1 " EQ $end
$var wire 1 ! GT $end
$var wire 1 ' t1 $end
$upscope $end
$upscope $end
$enddefinitions $end
#0
$dumpvars
0'
b1 &
b10 %
b1 $
b10 #
0"
1!
$end
#10
0!
1"
1'
b11 $
b11 &
b11 #
b11 %
#20
0"
0'
b10 $
b10 &
b1 #
b1 %
#30
1!
1'
b0 $
b0 &
#40
0!
b1 $
b1 &
b0 #
b0 %
#50
1"
b0 $
b0 &
#60
0"
1!
0'
b10 #
b10 %
#70
1!
1'
b1 #
b1 %
#80
0'
b11 #
b11 %
#90
0!
b11 $
b11 &
b0 #
b0 %
