Project/And.v
module And(Out,A,B);
    input [3:0] A;
    input [3:0] B;
    output [3:0] Out;
    and g1(Out[3],A[3],B[3]);    
    and g2(Out[2],A[2],B[2]);
    and g3(Out[1],A[1],B[1]);
    and g4(Out[0],A[0],B[0]);
endmodule

Project/Verilog/Comparator.v
module Comparator(Greater,Equal,Less,A,B,En);
    input [3:0] A;
    input [3:0] B;
    input En;
    output Greater,Equal,Less;
    wire gt3,gt2,gt1,gt0,eq3,eq2,eq1,eq0,ls3,ls,ls1,ls0;
    wire b3c,b2c,b1c,b0c;
    wire tempLess;
    xnor g1(eq3,A[3],B[3]);
    xnor g2(eq2,A[2],B[2]);
    xnor g3(eq1,A[1],B[1]);
    xnor g4(eq0,A[0],B[0]);
    not g5(b3c,B[3]);
    not g6(b2c,B[2]);
    not g7(b1c,B[1]);
    not g8(b0c,B[0]);
    and g9(gt3,A[3],b3c);    
    and g10(gt2,A[2],b2c,eq3);
    and g11(gt1,A[1],b1c,eq3,eq2);
    and g12(gt0,A[0],b0c,eq3,eq2,eq1);
    or g13(tempGreater,gt0,gt1,gt2,gt3);
    and g14(Equal,eq0,eq1,eq2,eq3,En);
    and g15(Greater,tempGreater,En);
    nor g16(tempLess,Greater,Equal);
    and g17(Less,tempLess,En);
endmodule

Project/Verilog/AdderSubtractor.v
module fullAdder(Cout,S,A,B,Cin);
    input A,B,Cin;
    output Cout,S;
    wire S1out,C1out,C2out;
    xor g1(S1out,A,B);
    xor g2(S,S1out,Cin);
    and g3(C1out,A,B);
    and g4(C2out,S1out,Cin);
    or g5(Cout,C1out,C2out);
endmodule

module AdderSubtractor(Sum,Carry,A,B,M);
    input [3:0] A;
    input [3:0] B;
    input M;
    output [3:0] Sum;
    output Carry;
    wire Cout0,Cout1,Cout2;
    wire B3,B2,B1,B0;
    xor g1(B0,M,B[0]);
    xor g2(B1,M,B[1]);
    xor g3(B2,M,B[2]);
    xor g4(B3,M,B[3]);
    fullAdder S0(Cout0,Sum[0],A[0],B0,M);
    fullAdder S1(Cout1,Sum[1],A[1],B1,Cout0);
    fullAdder S2(Cout2,Sum[2],A[2],B2,Cout1);
    fullAdder S3(Carry,Sum[3],A[3],B3,Cout2);
endmodule

Project/Verilog/Enable.v
module Enable(Aout,Bout,A,B,Ein);
    input [3:0] A;
    input [3:0] B;
    input Ein;
    output [3:0] Aout;
    output [3:0] Bout;
    and g1(Aout[3],A[3],Ein);
    and g2(Aout[2],A[2],Ein);
    and g3(Aout[1],A[1],Ein);
    and g4(Aout[0],A[0],Ein);
    and g5(Bout[3],B[3],Ein);
    and g6(Bout[2],B[2],Ein);
    and g7(Bout[1],B[1],Ein);
    and g8(Bout[0],B[0],Ein);
endmodule

Project/Decoder.v
module Decoder(D,S);
    input [1:0] S;
    output [3:0] D;
    wire Sc0,Sc1;
    not g1(Sc0,S[0]);
    not g2(Sc1,S[1]);
    and g3(D[0],Sc0,Sc1);
    and g4(D[1],S[0],Sc1);
    and g5(D[2],Sc0,S[1]);
    and g6(D[3],S[0],S[1]);
endmodule

Project/Verilog/ALU.v
`include "Enable.v"
`include "AdderSubtractor.v"
`include "Comparator.v"
`include "And.v"
`include "Decoder.v"

module ALU(CarryOut,Out,A,B,S);
    output CarryOut;
    output [3:0] Out;
    input [3:0] A;
    input [3:0] B;
    input [1:0] S;
    wire [3:0] SumAdd;
    wire Greater,Equal,Less;
    wire [3:0] OutAnd;
    wire [3:0] D;
    wire [3:0] AinAdd;
    wire [3:0] BinAdd;
    wire [3:0] AinComp;
    wire [3:0] BinComp;
    wire [3:0] AinAnd;
    wire [3:0] BinAnd;
    wire t1;
    Decoder D1(D,S);
    or g1(t1,D[0],D[1]);
    Enable eAnd(AinAnd,BinAnd,A,B,D[3]);
    Enable eComp(AinComp,BinComp,A,B,D[2]);
    Enable eAdd(AinAdd,BinAdd,A,B,t1);
    AdderSubtractor adder(SumAdd,CarryOut,AinAdd,BinAdd,D[1]);
    Comparator comp(Greater,Equal,Less,AinComp,BinComp,D[2]);
    And A1(OutAnd,AinAnd,BinAnd);
    or g2(Out[0],SumAdd[0],Equal,OutAnd[0]);
    or g3(Out[1],SumAdd[1],Less,OutAnd[1]);
    or g4(Out[2],SumAdd[2],Greater,OutAnd[2]);
    or g5(Out[3],SumAdd[3],OutAnd[3]);
endmodule

Project/Verilog/tb_ALU.v
`include "ALU.v"

module tb_ALU;
    reg [3:0] A;
    reg [3:0] B;
    reg [1:0] S;
    wire [3:0] Out;
    wire CarryOut;
    ALU DUT(CarryOut,Out,A,B,S);
    initial begin
        $dumpfile("tb_ALU.vcd");
        $dumpvars(0,tb_ALU);
        A = 4'b1001;
        B = 4'b0101;
        S = 2'b01;
        #10; 
        A = 4'b1100;
        B = 4'b1100;
        S = 2'b00;
        #10;
        A = 4'b0100;
        B = 4'b1001;
        S = 2'b00;
        #10;
        A = 4'b0101;
        B = 4'b0001;
        S = 2'b00;
        #10
        A = 4'b0010;
        B = 4'b0111;
        S = 2'b00;
        #10
        A = 4'b0011;
        B = 4'b0011;
        S = 2'b01;
        #10
        A = 4'b1001;
        B = 4'b0011;
        S = 2'b01;
        #10
        A = 4'b0110;
        B = 4'b1000;
        S = 2'b00;
        #10
        A = 4'b1111;
        B = 4'b0000;
        S = 2'b01;
        #10
        A = 4'b0000;
        B = 4'b1111;
        S = 2'b00;
        #10
        A = 4'b1001;
        B = 4'b0101;
        S = 2'b01;
        #10; 
        A = 4'b1100;
        B = 4'b1100;
        S = 2'b10;
        #10;
        A = 4'b0100;
        B = 4'b1001;
        S = 2'b10;
        #10;
        A = 4'b0101;
        B = 4'b0001;
        S = 2'b10;
        #10
        A = 4'b0010;
        B = 4'b0111;
        S = 2'b10;
        #10
        A = 4'b0011;
        B = 4'b0011;
        S = 2'b10;
        #10
        A = 4'b1001;
        B = 4'b0011;
        S = 2'b10;
        #10
        A = 4'b0110;
        B = 4'b1000;
        S = 2'b10;
        #10
        A = 4'b1111;
        B = 4'b0000;
        S = 2'b10;
        #10
        A = 4'b0000;
        B = 4'b1111;
        S = 2'b10;
        #10
        A = 4'b1001;
        B = 4'b0101;
        S = 2'b10;
        #10; 
        A = 4'b1100;
        B = 4'b1100;
        S = 2'b11;
        #10;
        A = 4'b0100;
        B = 4'b1001;
        S = 2'b11;
        #10;
        A = 4'b0101;
        B = 4'b0001;
        S = 2'b11;
        #10
        A = 4'b0010;
        B = 4'b0111;
        S = 2'b11;
        #10
        A = 4'b0011;
        B = 4'b0011;
        S = 2'b11;
        #10
        A = 4'b1001;
        B = 4'b0011;
        S = 2'b11;
        #10
        A = 4'b0110;
        B = 4'b1000;
        S = 2'b11;
        #10
        A = 4'b1111;
        B = 4'b0000;
        S = 2'b11;
        #10
        A = 4'b0000;
        B = 4'b1111;
        S = 2'b11;
        #10
        $finish;
    end
endmodule

Project/Verilog/tb_ALU.vcd
$date
	Wed Oct 25 16:17:08 2023
$end
$version
	Icarus Verilog
$end
$timescale
	1s
$end
$scope module tb_ALU $end
$var wire 4 ! Out [3:0] $end
$var wire 1 " CarryOut $end
$var reg 4 # A [3:0] $end
$var reg 4 $ B [3:0] $end
$var reg 2 % S [1:0] $end
$scope module DUT $end
$var wire 4 & A [3:0] $end
$var wire 4 ' B [3:0] $end
$var wire 2 ( S [1:0] $end
$var wire 1 ) t1 $end
$var wire 4 * SumAdd [3:0] $end
$var wire 4 + OutAnd [3:0] $end
$var wire 4 , Out [3:0] $end
$var wire 1 - Less $end
$var wire 1 . Greater $end
$var wire 1 / Equal $end
$var wire 4 0 D [3:0] $end
$var wire 1 " CarryOut $end
$var wire 4 1 BinComp [3:0] $end
$var wire 4 2 BinAnd [3:0] $end
$var wire 4 3 BinAdd [3:0] $end
$var wire 4 4 AinComp [3:0] $end
$var wire 4 5 AinAnd [3:0] $end
$var wire 4 6 AinAdd [3:0] $end
$scope module A1 $end
$var wire 4 7 Out [3:0] $end
$var wire 4 8 B [3:0] $end
$var wire 4 9 A [3:0] $end
$upscope $end
$scope module D1 $end
$var wire 2 : S [1:0] $end
$var wire 1 ; Sc0 $end
$var wire 1 < Sc1 $end
$var wire 4 = D [3:0] $end
$upscope $end
$scope module adder $end
$var wire 1 > B0 $end
$var wire 1 ? B1 $end
$var wire 1 @ B2 $end
$var wire 1 A B3 $end
$var wire 1 B M $end
$var wire 4 C Sum [3:0] $end
$var wire 1 D Cout2 $end
$var wire 1 E Cout1 $end
$var wire 1 F Cout0 $end
$var wire 1 " Carry $end
$var wire 4 G B [3:0] $end
$var wire 4 H A [3:0] $end
$scope module S0 $end
$var wire 1 I A $end
$var wire 1 > B $end
$var wire 1 J C1out $end
$var wire 1 K C2out $end
$var wire 1 B Cin $end
$var wire 1 F Cout $end
$var wire 1 L S $end
$var wire 1 M S1out $end
$upscope $end
$scope module S1 $end
$var wire 1 N A $end
$var wire 1 ? B $end
$var wire 1 O C1out $end
$var wire 1 P C2out $end
$var wire 1 F Cin $end
$var wire 1 E Cout $end
$var wire 1 Q S $end
$var wire 1 R S1out $end
$upscope $end
$scope module S2 $end
$var wire 1 S A $end
$var wire 1 @ B $end
$var wire 1 T C1out $end
$var wire 1 U C2out $end
$var wire 1 E Cin $end
$var wire 1 D Cout $end
$var wire 1 V S $end
$var wire 1 W S1out $end
$upscope $end
$scope module S3 $end
$var wire 1 X A $end
$var wire 1 A B $end
$var wire 1 Y C1out $end
$var wire 1 Z C2out $end
$var wire 1 D Cin $end
$var wire 1 " Cout $end
$var wire 1 [ S $end
$var wire 1 \ S1out $end
$upscope $end
$upscope $end
$scope module comp $end
$var wire 1 ] En $end
$var wire 1 / Equal $end
$var wire 1 . Greater $end
$var wire 1 - Less $end
$var wire 1 ^ b0c $end
$var wire 1 _ b1c $end
$var wire 1 ` b2c $end
$var wire 1 a b3c $end
$var wire 1 b eq0 $end
$var wire 1 c eq1 $end
$var wire 1 d eq2 $end
$var wire 1 e eq3 $end
$var wire 1 f gt0 $end
$var wire 1 g gt1 $end
$var wire 1 h gt2 $end
$var wire 1 i gt3 $end
$var wire 1 j tempLess $end
$var wire 4 k B [3:0] $end
$var wire 4 l A [3:0] $end
$upscope $end
$scope module eAdd $end
$var wire 4 m A [3:0] $end
$var wire 4 n B [3:0] $end
$var wire 1 ) Ein $end
$var wire 4 o Bout [3:0] $end
$var wire 4 p Aout [3:0] $end
$upscope $end
$scope module eAnd $end
$var wire 4 q A [3:0] $end
$var wire 4 r B [3:0] $end
$var wire 1 s Ein $end
$var wire 4 t Bout [3:0] $end
$var wire 4 u Aout [3:0] $end
$upscope $end
$scope module eComp $end
$var wire 4 v A [3:0] $end
$var wire 4 w B [3:0] $end
$var wire 1 x Ein $end
$var wire 4 y Bout [3:0] $end
$var wire 4 z Aout [3:0] $end
$upscope $end
$upscope $end
$upscope $end
$enddefinitions $end
#0
$dumpvars
b0 z
b0 y
0x
b101 w
b1001 v
b0 u
b0 t
0s
b101 r
b1001 q
b1001 p
b101 o
b101 n
b1001 m
b0 l
b0 k
1j
0i
0h
0g
0f
1e
1d
1c
1b
1a
1`
1_
1^
0]
0\
0[
0Z
1Y
1X
0W
1V
0U
0T
0S
1R
0Q
1P
0O
0N
1M
0L
1K
0J
1I
b1001 H
b101 G
1F
1E
0D
b100 C
1B
1A
0@
1?
0>
b10 =
1<
0;
b1 :
b0 9
b0 8
b0 7
b1001 6
b0 5
b0 4
b101 3
b0 2
b0 1
b10 0
0/
0.
0-
b100 ,
b0 +
b100 *
1)
b1 (
b101 '
b1001 &
b1 %
b101 $
b1001 #
1"
b100 !
$end
#10
1"
0E
1Y
1A
b1000 !
b1000 ,
1[
0P
1X
1D
1T
0R
0F
b1000 *
b1000 C
0V
0U
1@
0?
0K
1)
0W
0M
0B
1S
0I
1;
b1 0
b1 =
b1100 3
b1100 G
b1100 o
b1100 6
b1100 H
b1100 p
b0 %
b0 (
b0 :
b1100 $
b1100 '
b1100 n
b1100 r
b1100 w
b1100 #
b1100 &
b1100 m
b1100 q
b1100 v
#20
b1101 !
b1101 ,
1V
0D
1L
1W
0T
1M
b1101 *
b1101 C
1[
0Z
0"
0@
1>
1\
0Y
0X
b1001 3
b1001 G
b1001 o
b100 6
b100 H
b100 p
b1001 $
b1001 '
b1001 n
b1001 r
b1001 w
b100 #
b100 &
b100 m
b100 q
b100 v
#30
b110 !
b110 ,
0[
1Q
0\
b110 *
b110 C
0L
1F
0A
0M
1J
1I
b1 3
b1 G
b1 o
b101 6
b101 H
b101 p
b1 $
b1 '
b1 n
b1 r
b1 w
b101 #
b101 &
b101 m
b101 q
b101 v
#40
1[
1D
b1001 !
b1001 ,
1U
0Q
1E
1O
0V
b1001 *
b1001 C
1L
0F
1@
1?
1W
0R
1M
0J
0S
1N
0I
b111 3
b111 G
b111 o
b10 6
b10 H
b10 p
b111 $
b111 '
b111 n
b111 r
b111 w
b10 #
b10 &
b10 m
b10 q
b10 v
#50
1D
0V
1U
b0 !
b0 ,
1E
1"
0Q
0[
1Z
b0 *
b0 C
0L
1K
1P
1R
0O
1\
1F
0?
1A
0>
1M
0J
1B
1I
0;
b10 0
b10 =
b11 3
b11 G
b11 o
b11 6
b11 H
b11 p
b1 %
b1 (
b1 :
b11 $
b11 '
b11 n
b11 r
b11 w
b11 #
b11 &
b11 m
b11 q
b11 v
#60
0D
b110 !
b110 ,
1V
0U
0E
0[
0Z
b110 *
b110 C
1Q
0P
0\
1Y
0R
1X
0N
b1001 6
b1001 H
b1001 p
b1001 #
b1001 &
b1001 m
b1001 q
b1001 v
#70
1[
1A
b1110 !
b1110 ,
0U
0E
0F
0Z
0"
1V
0D
b1110 *
b1110 C
1Q
0P
0@
0K
1)
1\
0Y
1W
0T
1R
0M
0B
0X
1S
1N
0I
1;
b1 0
b1 =
b1000 3
b1000 G
b1000 o
b110 6
b110 H
b110 p
b0 %
b0 (
b0 :
b1000 $
b1000 '
b1000 n
b1000 r
b1000 w
b110 #
b110 &
b110 m
b110 q
b110 v
#80
b1111 !
b1111 ,
1D
1E
1L
0W
1T
0R
1O
1J
1F
b1111 *
b1111 C
1[
1"
1@
1?
1>
0K
0\
1Y
0M
1B
1X
1I
0;
b10 0
b10 =
b0 3
b0 G
b0 o
b1111 6
b1111 H
b1111 p
b1 %
b1 (
b1 :
b0 $
b0 '
b0 n
b0 r
b0 w
b1111 #
b1111 &
b1111 m
b1111 q
b1111 v
#90
b1111 !
b1111 ,
1[
1V
1Q
b1111 *
b1111 C
1L
1A
1@
1?
1>
0"
0D
0E
0F
1)
1\
0Y
1W
0T
1R
0O
1M
0J
0B
0X
0S
0N
0I
1;
b1 0
b1 =
b1111 3
b1111 G
b1111 o
b0 6
b0 H
b0 p
b0 %
b0 (
b0 :
b1111 $
b1111 '
b1111 n
b1111 r
b1111 w
b0 #
b0 &
b0 m
b0 q
b0 v
#100
b100 !
b100 ,
1E
1V
0L
1K
0Q
1P
0W
b100 *
b100 C
0[
1"
1F
0@
0>
0\
1Y
1M
0J
1B
1X
1I
0;
b10 0
b10 =
b101 3
b101 G
b101 o
b1001 6
b1001 H
b1001 p
b1 %
b1 (
b1 :
b101 $
b101 '
b101 n
b101 r
b101 w
b1001 #
b1001 &
b1001 m
b1001 q
b1001 v
#110
0"
0j
0a
0`
0E
0Y
0A
0[
1/
b1 !
b1 ,
0P
0X
0D
0-
b1100 4
b1100 l
b1100 z
b1100 1
b1100 k
b1100 y
0T
0R
0F
b0 *
b0 C
0V
0U
1]
1x
0@
0?
0K
0)
0W
0M
0B
0S
0I
1;
0<
b100 0
b100 =
b0 3
b0 G
b0 o
b0 6
b0 H
b0 p
b10 %
b10 (
b10 :
b1100 $
b1100 '
b1100 n
b1100 r
b1100 w
b1100 #
b1100 &
b1100 m
b1100 q
b1100 v
#120
1-
1j
b10 !
b10 ,
0/
1`
0d
0^
0b
0e
b1001 1
b1001 k
b1001 y
b100 4
b100 l
b100 z
b1001 $
b1001 '
b1001 n
b1001 r
b1001 w
b100 #
b100 &
b100 m
b100 q
b100 v
#130
0-
0j
b100 !
b100 ,
1.
1h
1a
1e
1b
b1 1
b1 k
b1 y
b101 4
b101 l
b101 z
b1 $
b1 '
b1 n
b1 r
b1 w
b101 #
b101 &
b101 m
b101 q
b101 v
#140
1-
1j
b10 !
b10 ,
0.
0`
0_
0h
0b
b111 1
b111 k
b111 y
b10 4
b10 l
b10 z
b111 $
b111 '
b111 n
b111 r
b111 w
b10 #
b10 &
b10 m
b10 q
b10 v
#150
0-
0j
b1 !
b1 ,
1/
1`
1d
1b
b11 1
b11 k
b11 y
b11 4
b11 l
b11 z
b11 $
b11 '
b11 n
b11 r
b11 w
b11 #
b11 &
b11 m
b11 q
b11 v
#160
b100 !
b100 ,
0/
1.
1i
0e
0c
b1001 4
b1001 l
b1001 z
b1001 #
b1001 &
b1001 m
b1001 q
b1001 v
#170
1-
1j
b10 !
b10 ,
0.
0a
1_
1^
0i
0d
b1000 1
b1000 k
b1000 y
b110 4
b110 l
b110 z
b1000 $
b1000 '
b1000 n
b1000 r
b1000 w
b110 #
b110 &
b110 m
b110 q
b110 v
#180
0-
0j
b100 !
b100 ,
1.
1i
1a
0b
b0 1
b0 k
b0 y
b1111 4
b1111 l
b1111 z
b0 $
b0 '
b0 n
b0 r
b0 w
b1111 #
b1111 &
b1111 m
b1111 q
b1111 v
#190
1-
1j
b10 !
b10 ,
0.
0a
0`
0_
0^
0i
b1111 1
b1111 k
b1111 y
b0 4
b0 l
b0 z
b1111 $
b1111 '
b1111 n
b1111 r
b1111 w
b0 #
b0 &
b0 m
b0 q
b0 v
#200
0-
0j
b100 !
b100 ,
1.
1i
1a
1_
1c
1b
b101 1
b101 k
b101 y
b1001 4
b1001 l
b1001 z
b101 $
b101 '
b101 n
b101 r
b101 w
b1001 #
b1001 &
b1001 m
b1001 q
b1001 v
#210
1`
1j
b1100 !
b1100 ,
b1100 +
b1100 7
0.
0i
0]
0x
b1100 5
b1100 9
b1100 u
b1100 2
b1100 8
b1100 t
1a
1e
1^
1d
1s
0;
b1000 0
b1000 =
b0 1
b0 k
b0 y
b0 4
b0 l
b0 z
b11 %
b11 (
b11 :
b1100 $
b1100 '
b1100 n
b1100 r
b1100 w
b1100 #
b1100 &
b1100 m
b1100 q
b1100 v
#220
b0 !
b0 ,
b0 +
b0 7
b1001 2
b1001 8
b1001 t
b100 5
b100 9
b100 u
b1001 $
b1001 '
b1001 n
b1001 r
b1001 w
b100 #
b100 &
b100 m
b100 q
b100 v
#230
b1 !
b1 ,
b1 +
b1 7
b1 2
b1 8
b1 t
b101 5
b101 9
b101 u
b1 $
b1 '
b1 n
b1 r
b1 w
b101 #
b101 &
b101 m
b101 q
b101 v
#240
b10 !
b10 ,
b10 +
b10 7
b111 2
b111 8
b111 t
b10 5
b10 9
b10 u
b111 $
b111 '
b111 n
b111 r
b111 w
b10 #
b10 &
b10 m
b10 q
b10 v
#250
b11 !
b11 ,
b11 +
b11 7
b11 2
b11 8
b11 t
b11 5
b11 9
b11 u
b11 $
b11 '
b11 n
b11 r
b11 w
b11 #
b11 &
b11 m
b11 q
b11 v
#260
b1 !
b1 ,
b1 +
b1 7
b1001 5
b1001 9
b1001 u
b1001 #
b1001 &
b1001 m
b1001 q
b1001 v
#270
b0 !
b0 ,
b0 +
b0 7
b1000 2
b1000 8
b1000 t
b110 5
b110 9
b110 u
b1000 $
b1000 '
b1000 n
b1000 r
b1000 w
b110 #
b110 &
b110 m
b110 q
b110 v
#280
b0 2
b0 8
b0 t
b1111 5
b1111 9
b1111 u
b0 $
b0 '
b0 n
b0 r
b0 w
b1111 #
b1111 &
b1111 m
b1111 q
b1111 v
#290
b1111 2
b1111 8
b1111 t
b0 5
b0 9
b0 u
b1111 $
b1111 '
b1111 n
b1111 r
b1111 w
b0 #
b0 &
b0 m
b0 q
b0 v
