Project/Verilog/Comparator.v
module Comparator(Greater,Equal,Less,A,B,En);
    input [3:0] A;
    input [3:0] B;
    input En;
    output Greater,Equal,Less;
    wire gt3,gt2,gt1,gt0,eq3,eq2,eq1,eq0,ls3,ls,ls1,ls0;
    wire b3c,b2c,b1c,b0c;
    wire tempLess;
    xnor g1(eq3,A[3],B[3]);
    xnor g2(eq2,A[2],B[2]);
    xnor g3(eq1,A[1],B[1]);
    xnor g4(eq0,A[0],B[0]);
    not g5(b3c,B[3]);
    not g6(b2c,B[2]);
    not g7(b1c,B[1]);
    not g8(b0c,B[0]);
    and g9(gt3,A[3],b3c);    
    and g10(gt2,A[2],b2c,eq3);
    and g11(gt1,A[1],b1c,eq3,eq2);
    and g12(gt0,A[0],b0c,eq3,eq2,eq1);
    or g13(Greater,gt0,gt1,gt2,gt3);
    and g14(Equal,eq0,eq1,eq2,eq3,En);
    nor g15(tempLess,Greater,Equal);
    and g16(Less,tempLess,En);
endmodule

Project/Verilog/tb_Comparator.v
`include "Comparator.v"

module tb_Comparator;
    reg [3:0] A;
    reg [3:0] B;
    reg En;
    wire Equal, Greater, Less;
    Comparator DUT(Greater,Equal,Less,A,B,En);
    initial begin
        $dumpfile("tb_Comparator.vcd");
        $dumpvars(0,tb_Comparator);
        $monitor ($time, "En=%b A=%b, B=%b, Equal=%b, Greater=%b, Less=%b", En, A, B, Equal, Greater, Less);
        A = 4'b1001;
        B = 4'b0101;
        En = 1;
        #10; 
        A = 4'b1100;
        B = 4'b1100;
        En = 1;
        #10;
        A = 4'b0100;
        B = 4'b1001;
        En = 1;
        #10;
        A = 4'b0101;
        B = 4'b0001;
        En = 1;
        #10
        A = 4'b0010;
        B = 4'b0111;
        En = 1;
        #10
        A = 4'b0011;
        B = 4'b0011;
        En = 0;
        #10
        A = 4'b1001;
        B = 4'b0011;
        En = 1;
        #10
        A = 4'b0110;
        B = 4'b1000;
        En = 1;
        #10
        A = 4'b1111;
        B = 4'b0000;
        En = 0;
        #10
        A = 4'b0000;
        B = 4'b1111;
        En = 1;
        #10
        $finish;
    end
endmodule

Project/Verilog/tb_Comparator.vcd
$date
	Tue Oct 24 11:56:58 2023
$end
$version
	Icarus Verilog
$end
$timescale
	1s
$end
$scope module tb_Comparator $end
$var wire 1 ! Less $end
$var wire 1 " Greater $end
$var wire 1 # Equal $end
$var reg 4 $ A [3:0] $end
$var reg 4 % B [3:0] $end
$var reg 1 & En $end
$scope module DUT $end
$var wire 4 ' A [3:0] $end
$var wire 4 ( B [3:0] $end
$var wire 1 & En $end
$var wire 1 # Equal $end
$var wire 1 " Greater $end
$var wire 1 ! Less $end
$var wire 1 ) b0c $end
$var wire 1 * b1c $end
$var wire 1 + b2c $end
$var wire 1 , b3c $end
$var wire 1 - eq0 $end
$var wire 1 . eq1 $end
$var wire 1 / eq2 $end
$var wire 1 0 eq3 $end
$var wire 1 1 gt0 $end
$var wire 1 2 gt1 $end
$var wire 1 3 gt2 $end
$var wire 1 4 gt3 $end
$var wire 1 5 tempLess $end
$upscope $end
$upscope $end
$enddefinitions $end
#0
$dumpvars
05
14
03
02
01
00
0/
1.
1-
1,
0+
1*
0)
b101 (
b1001 '
1&
b101 %
b1001 $
0#
1"
0!
$end
#10
0"
1#
04
10
0,
1)
1/
b1100 %
b1100 (
b1100 $
b1100 '
#20
1!
15
0#
0/
0-
1+
0)
00
b1001 %
b1001 (
b100 $
b100 '
#30
0!
05
1"
13
10
1,
1-
b1 %
b1 (
b101 $
b101 '
#40
1!
15
0"
0+
0*
0-
03
b111 %
b111 (
b10 $
b10 '
#50
1/
1+
1-
0!
0&
b11 %
b11 (
b11 $
b11 '
#60
05
1"
0#
00
0.
14
0!
1&
b1001 $
b1001 '
#70
1!
15
0"
0,
1*
1)
0/
04
b1000 %
b1000 (
b110 $
b110 '
#80
05
1"
14
1,
0-
0!
0&
b0 %
b0 (
b1111 $
b1111 '
#90
1!
15
0"
0,
0+
0*
0)
04
1&
b1111 %
b1111 (
b0 $
b0 '
