Project/AdderSubtractor.v
module fullAdder(Cout,S,A,B,Cin);
    input A,B,Cin;
    output Cout,S;
    wire S1out,C1out,C2out;
    xor g1(S1out,A,B);
    xor g2(S,S1out,Cin);
    and g3(C1out,A,B);
    and g4(C2out,S1out,Cin);
    or g5(Cout,C1out,C2out);
endmodule

module AdderSubtractor(Sum,Carry,A,B,M);
    input [3:0] A;
    input [3:0] B;
    input M;
    output [3:0] Sum;
    output Carry;
    wire Cout0,Cout1,Cout2;
    wire B3,B2,B1,B0;
    xor g1(B2,M,B[2]);
    xor g2(B1,M,B[1]);
    xor g3(B3,M,B[3]);
    xor g4(B0,M,B[0]);
    fullAdder ins1(Cout0,Sum[0],A[0],B0,M);
    fullAdder ins2(Cout1,Sum[1],A[1],B1,Cout0);
    fullAdder ins3(Cout2,Sum[2],A[2],B2,Cout1);
    fullAdder ins4(Carry,Sum[3],A[3],B3,Cout2);
endmodule

Project/tb_AdderSubractor.v
`include "AdderSubtractor.v"

module tb_AdderSubractor;
    reg [3:0] A;
    reg [3:0] B;
    reg M;
    wire [3:0] Sum;
    wire Carry;
    AdderSubtractor DUT(Sum,Carry,A,B,M);
    initial begin
        $dumpfile("tb_AdderSubractor.vcd");
        $dumpvars(0,tb_AdderSubractor);
        $monitor ($time, " A=%b, B=%b, M=%b, Sum=%b, Carry=%b", A, B, M, Sum, Carry);
        A = 4'b1001;
        B = 4'b0101;
        M = 1;
        #10; 
        A = 4'b1100;
        B = 4'b1100;
        M = 0;
        #10;
        A = 4'b0100;
        B = 4'b1001;
        M = 0;
        #10;
        A = 4'b0101;
        B = 4'b0001;
        M = 0;
        #10
        A = 4'b0010;
        B = 4'b0111;
        M = 0;
        #10
        A = 4'b0011;
        B = 4'b0011;
        M = 1;
        #10
        A = 4'b1001;
        B = 4'b0011;
        M = 1;
        #10
        A = 4'b0110;
        B = 4'b1000;
        M = 0;
        #10
        A = 4'b1111;
        B = 4'b0000;
        M = 1;
        #10
        A = 4'b0000;
        B = 4'b1111;
        M = 0;
        #10
        $finish;
    end
endmodule

Project/tb_AdderSubractor.vcd
$date
	Thu Sep 28 16:07:46 2023
$end
$version
	Icarus Verilog
$end
$timescale
	1s
$end
$scope module tb_AdderSubractor $end
$var wire 4 ! Sum [3:0] $end
$var wire 1 " Carry $end
$var reg 4 # A [3:0] $end
$var reg 4 $ B [3:0] $end
$var reg 1 % M $end
$scope module DUT $end
$var wire 4 & A [3:0] $end
$var wire 4 ' B [3:0] $end
$var wire 1 ( B0 $end
$var wire 1 ) B1 $end
$var wire 1 * B2 $end
$var wire 1 + B3 $end
$var wire 1 % M $end
$var wire 4 , Sum [3:0] $end
$var wire 1 - Cout2 $end
$var wire 1 . Cout1 $end
$var wire 1 / Cout0 $end
$var wire 1 " Carry $end
$scope module ins1 $end
$var wire 1 0 A $end
$var wire 1 ( B $end
$var wire 1 1 C1out $end
$var wire 1 2 C2out $end
$var wire 1 % Cin $end
$var wire 1 / Cout $end
$var wire 1 3 S $end
$var wire 1 4 S1out $end
$upscope $end
$scope module ins2 $end
$var wire 1 5 A $end
$var wire 1 ) B $end
$var wire 1 6 C1out $end
$var wire 1 7 C2out $end
$var wire 1 / Cin $end
$var wire 1 . Cout $end
$var wire 1 8 S $end
$var wire 1 9 S1out $end
$upscope $end
$scope module ins3 $end
$var wire 1 : A $end
$var wire 1 * B $end
$var wire 1 ; C1out $end
$var wire 1 < C2out $end
$var wire 1 . Cin $end
$var wire 1 - Cout $end
$var wire 1 = S $end
$var wire 1 > S1out $end
$upscope $end
$scope module ins4 $end
$var wire 1 ? A $end
$var wire 1 + B $end
$var wire 1 @ C1out $end
$var wire 1 A C2out $end
$var wire 1 - Cin $end
$var wire 1 " Cout $end
$var wire 1 B S $end
$var wire 1 C S1out $end
$upscope $end
$upscope $end
$upscope $end
$enddefinitions $end
#0
$dumpvars
0C
0B
0A
1@
1?
0>
1=
0<
0;
0:
19
08
17
06
05
14
03
12
01
10
1/
1.
0-
b100 ,
1+
0*
1)
0(
b101 '
b1001 &
1%
b101 $
b1001 #
1"
b100 !
$end
#10
0=
0.
1B
07
1-
09
0/
04
1;
1*
0)
b1000 !
b1000 ,
03
02
00
1:
0%
b1100 $
b1100 '
b1100 #
b1100 &
#20
1=
0-
13
1>
0;
14
b1101 !
b1101 ,
1B
0A
0"
0*
1(
1C
0@
0?
b1001 $
b1001 '
b100 #
b100 &
#30
0B
18
0C
b110 !
b110 ,
03
1/
0+
04
11
10
b1 $
b1 '
b101 #
b101 &
#40
1B
1-
1<
1.
16
13
0/
08
07
b1001 !
b1001 ,
0=
1*
1)
14
01
09
1>
00
15
0:
b111 $
b111 '
b10 #
b10 &
#50
1"
0B
1A
17
19
06
1C
1/
0)
1+
0(
b0 !
b0 ,
03
12
10
1%
b11 $
b11 '
b11 #
b11 &
#60
0-
1=
0<
0.
18
07
b110 !
b110 ,
0B
0A
09
0C
1@
05
1?
b1001 #
b1001 &
#70
1B
0"
0/
04
19
1C
0@
0*
b1110 !
b1110 ,
03
02
00
15
1:
0?
0%
b1000 $
b1000 '
b110 #
b110 &
#80
1-
1.
1/
1B
1"
0>
1;
09
16
11
0C
1@
1*
1)
1(
b1111 !
b1111 ,
13
10
1?
1%
b0 $
b0 '
b1111 #
b1111 &
#90
0/
18
07
0.
1=
0<
0-
1B
0A
0"
14
01
19
06
1>
0;
1C
0@
b1111 !
b1111 ,
13
00
05
0:
0?
0%
b1111 $
b1111 '
b0 #
b0 &
