Project/and.v
module comparator(Out,A,B);
    input [3:0] A;
    input [3:0] B;
    output [3:0] Out;
    and g1(Out[3],A[3],B[3]);    
    and g2(Out[2],A[2],B[2]);
    and g3(Out[1],A[1],B[1]);
    and g4(Out[0],A[0],B[0]);
endmodule

Project/tb_and.v
`include "and.v"

module tb_and;
    reg [3:0] A;
    reg [3:0] B;
    wire [3:0] Out;
    comparator DUT(Out,A,B);
    initial begin
        $dumpfile("tb_and.vcd");
        $dumpvars(0,tb_and);
        $monitor ($time, " A=%b, B=%b, A.B=%b", A, B, Out);
        A = 4'b1001;
        B = 4'b0101;
        #10; 
        A = 4'b1100;
        B = 4'b1100;
        #10;
        A = 4'b0100;
        B = 4'b1001;
        #10;
        A = 4'b0101;
        B = 4'b0001;
        #10
        A = 4'b0010;
        B = 4'b0111;
        #10
        A = 4'b0011;
        B = 4'b0011;
        #10
        A = 4'b1001;
        B = 4'b0011;
        #10
        A = 4'b0110;
        B = 4'b1000;
        #10
        A = 4'b1111;
        B = 4'b0000;
        #10
        A = 4'b0000;
        B = 4'b1111;
        #10
        $finish;
    end
endmodule

Project/tb_and.vcd
$date
	Thu Sep 28 14:44:26 2023
$end
$version
	Icarus Verilog
$end
$timescale
	1s
$end
$scope module tb_and $end
$var wire 4 ! Out [3:0] $end
$var reg 4 " A [3:0] $end
$var reg 4 # B [3:0] $end
$scope module DUT $end
$var wire 4 $ A [3:0] $end
$var wire 4 % B [3:0] $end
$var wire 4 & Out [3:0] $end
$upscope $end
$upscope $end
$enddefinitions $end
#0
$dumpvars
b1 &
b101 %
b1001 $
b101 #
b1001 "
b1 !
$end
#10
b1100 !
b1100 &
b1100 #
b1100 %
b1100 "
b1100 $
#20
b0 !
b0 &
b1001 #
b1001 %
b100 "
b100 $
#30
b1 !
b1 &
b1 #
b1 %
b101 "
b101 $
#40
b10 !
b10 &
b111 #
b111 %
b10 "
b10 $
#50
b11 !
b11 &
b11 #
b11 %
b11 "
b11 $
#60
b1 !
b1 &
b1001 "
b1001 $
#70
b0 !
b0 &
b1000 #
b1000 %
b110 "
b110 $
#80
b0 #
b0 %
b1111 "
b1111 $
#90
b1111 #
b1111 %
b0 "
b0 $
