Project/comparator.v
module comparator(Greater,Equal,Less,A,B);
    input [3:0] A;
    input [3:0] B;
    output Greater,Equal,Less;
    wire gt3,gt2,gt1,gt0,eq3,eq2,eq1,eq0,ls3,ls,ls1,ls0;
    wire b3c,b2c,b1c,b0c;
    xnor g1(eq3,A[3],B[3]);
    xnor g2(eq2,A[2],B[2]);
    xnor g3(eq1,A[1],B[1]);
    xnor g4(eq0,A[0],B[0]);
    not g5(b3c,B[3]);
    not g6(b2c,B[2]);
    not g7(b1c,B[1]);
    not g8(b0c,B[0]);
    and g9(gt3,A[3],b3c);    
    and g10(gt2,A[2],b2c,eq3);
    and g11(gt1,A[1],b1c,eq3,eq2);
    and g12(gt0,A[0],b0c,eq3,eq2,eq1);
    or g13(Greater,gt0,gt1,gt2,gt3);
    and g14(Equal,eq0,eq1,eq2,eq3);
    nor g15(Less,Greater,Equal);
endmodule

Project/tb_comparator.v
`include "comparator.v"

module tb_comparator;
    reg [3:0] A;
    reg [3:0] B;
    wire Equal, Greater, Less;
    comparator DUT(Greater,Equal,Less,A,B);
    initial begin
        $dumpfile("tb_comparator.vcd");
        $dumpvars(0,tb_comparator);
        $monitor ($time, " A=%b, B=%b, Equal=%b, Greater=%b, Less=%b", A, B, Equal, Greater, Less);
        A = 4'b1001;
        B = 4'b0101;
        #10; 
        A = 4'b1100;
        B = 4'b1100;
        #10;
        A = 4'b0100;
        B = 4'b1001;
        #10;
        A = 4'b0101;
        B = 4'b0001;
        #10
        A = 4'b0010;
        B = 4'b0111;
        #10
        A = 4'b0011;
        B = 4'b0011;
        #10
        A = 4'b1001;
        B = 4'b0011;
        #10
        A = 4'b0110;
        B = 4'b1000;
        #10
        A = 4'b1111;
        B = 4'b0000;
        #10
        A = 4'b0000;
        B = 4'b1111;
        #10
        $finish;
    end
endmodule

Project/tb_comparator.vcd
$date
	Thu Sep 28 14:36:13 2023
$end
$version
	Icarus Verilog
$end
$timescale
	1s
$end
$scope module tb_comparator $end
$var wire 1 ! Less $end
$var wire 1 " Greater $end
$var wire 1 # Equal $end
$var reg 4 $ A [3:0] $end
$var reg 4 % B [3:0] $end
$scope module DUT $end
$var wire 4 & A [3:0] $end
$var wire 4 ' B [3:0] $end
$var wire 1 # Equal $end
$var wire 1 " Greater $end
$var wire 1 ! Less $end
$var wire 1 ( b0c $end
$var wire 1 ) b1c $end
$var wire 1 * b2c $end
$var wire 1 + b3c $end
$var wire 1 , eq0 $end
$var wire 1 - eq1 $end
$var wire 1 . eq2 $end
$var wire 1 / eq3 $end
$var wire 1 0 gt0 $end
$var wire 1 1 gt1 $end
$var wire 1 2 gt2 $end
$var wire 1 3 gt3 $end
$upscope $end
$upscope $end
$enddefinitions $end
#0
$dumpvars
13
02
01
00
0/
0.
1-
1,
1+
0*
1)
0(
b101 '
b1001 &
b101 %
b1001 $
0#
1"
0!
$end
#10
0"
03
1#
1/
0+
1(
1.
b1100 %
b1100 '
b1100 $
b1100 &
#20
1!
0#
0.
0,
1*
0(
0/
b1001 %
b1001 '
b100 $
b100 &
#30
0!
1"
12
1/
1+
1,
b1 %
b1 '
b101 $
b101 &
#40
1!
0"
0*
0)
0,
02
b111 %
b111 '
b10 $
b10 &
#50
0!
1#
1.
1*
1,
b11 %
b11 '
b11 $
b11 &
#60
0#
1"
0/
0-
13
b1001 $
b1001 &
#70
1!
0"
0+
1)
1(
0.
03
b1000 %
b1000 '
b110 $
b110 &
#80
0!
1"
13
1+
0,
b0 %
b0 '
b1111 $
b1111 &
#90
1!
0"
0+
0*
0)
0(
03
b1111 %
b1111 '
b0 $
b0 &
