VLSI A1/Codes/q7.v
module q7 (
    input clk,
    input reset,
    input X,
    output reg Y
);
parameter s0 = 0,s1 = 1,s2 = 2;
    
reg[2:0] state,next_state;

always@(posedge clk)begin
  if(reset)begin
    state <= s0;
  end
  else begin
    state <= next_state;
  end
end

always@(state or X)begin
  case(state)
    s0:begin
      Y = 0;
      if(X) next_state = s1;
      else next_state = s0;
    end
    s1:begin
        Y = 1;
        if(X) next_state = s1;
        else next_state = s2;
    end
    s2:begin
      Y = 0;
      next_state = s2;
    end
    default:begin
      next_state = s0;
    end
  endcase
end
endmodule

VLSI A1/Codes/tb_q7.v
`include "q7.v"
`timescale 1ns/1ns
module tb_fsm;

reg clk,X;
reg rst_n;
wire Y;


q7 call(clk,rst_n,X,Y);

always #5 clk = ~clk;

initial begin
    $dumpfile("tb_q7.vcd");
    $dumpvars(0, tb_fsm);
end

always @(posedge clk) begin
    #5
    $display($time,"ns in = ",X," out =",Y); 
end

initial begin
    clk = 1;
    rst_n =1;
    X = 0;
end

initial begin
    #5;
    rst_n = 0;
    X = 1;
    #10
    rst_n = 0;
    X = 0;
    #10
    rst_n = 0;
    X = 1;
    #10
    rst_n = 0;
    X = 1;
    #10
    rst_n = 0;
    X = 0;
    #10
    rst_n = 1;
    #10 
    rst_n = 0;
    X = 0;
    #10
    rst_n = 0;
    X = 1;
    #10
    rst_n = 0;
    X = 1;
    #10
    $finish;
end
endmodule

VLSI A1/Codes/tb_q7.vcd
$date
	Sat Sep 16 22:24:32 2023
$end
$version
	Icarus Verilog
$end
$timescale
	1ns
$end
$scope module tb_fsm $end
$var wire 1 ! Y $end
$var reg 1 " X $end
$var reg 1 # clk $end
$var reg 1 $ rst_n $end
$scope module call $end
$var wire 1 " X $end
$var wire 1 # clk $end
$var wire 1 $ reset $end
$var reg 1 ! Y $end
$var reg 3 % next_state [2:0] $end
$var reg 3 & state [2:0] $end
$upscope $end
$upscope $end
$enddefinitions $end
#0
$dumpvars
b0 &
b0 %
1$
1#
0"
0!
$end
#5
b1 %
1"
0$
0#
#10
1!
b1 &
1#
#15
b10 %
0#
0"
#20
0!
b10 &
1#
#25
0#
1"
#30
1#
#35
0#
#40
1#
#45
0#
0"
#50
1#
#55
0#
1$
#60
b0 %
b0 &
1#
#65
0#
0$
#70
1#
#75
b1 %
0#
1"
#80
1!
b1 &
1#
